sas7bdat.py
sas7bdatx-2.2.3.3.data/scripts/sas7bdat_to_csv
sas7bdatx-2.2.3.3.dist-info/LICENSE
sas7bdatx-2.2.3.3.dist-info/METADATA
sas7bdatx-2.2.3.3.dist-info/WHEEL
sas7bdatx-2.2.3.3.dist-info/top_level.txt
sas7bdatx-2.2.3.3.dist-info/RECORD
