Metadata-Version: 2.1
Name: sas7bdatx
Version: 2.2.3.3
Summary: A sas7bdat file reader for Python
Home-page: https://github.com/kaellwen/sas7bdat.git
Author: Jared Hobbs, Yao Xiao
Author-email: kaellwen@gmail.com
License: MIT
Keywords: sas,sas7bdat,csv,converter
Classifier: Development Status :: 5 - Production/Stable
Classifier: Environment :: Console
Classifier: Intended Audience :: Developers
Classifier: Intended Audience :: Science/Research
Classifier: License :: OSI Approved :: MIT License
Classifier: Operating System :: OS Independent
Classifier: Programming Language :: Python :: 2.6
Classifier: Programming Language :: Python :: 2.7
Classifier: Programming Language :: Python :: 3
Classifier: Topic :: Text Processing
Classifier: Topic :: Utilities
License-File: LICENSE
Requires-Dist: six>=1.8.0
